[{"work_id": "peso_pluma_tito_double_p__gavil_n_ii", "platform": "spotify", "chart_name": "top_200", "region": "global", "date": "2023-06-23", "rank": 142, "streams": 1377119, "weeks_on_chart": 1, "peak_position": 142}, {"work_id": "peso_pluma_tito_double_p__gavil_n_ii", "platform": "spotify", "chart_name": "top_200", "region": "us", "date": "2023-06-23", "rank": 70, "streams": 498966, "weeks_on_chart": 1, "peak_position": 70}, {"work_id": "peso_pluma_tito_double_p__gavil_n_ii", "platform": "spotify", "chart_name": "top_200", "region": "us", "date": "2023-06-24", "rank": 154, "streams": 335182, "weeks_on_chart": 2, "peak_position": 70}, {"work_id": "peso_pluma_tito_double_p__gavil_n_ii", "platform": "spotify", "chart_name": "top_200", "region": "us", "date": "2023-06-26", "rank": 193, "streams": 283988, "weeks_on_chart": 3, "peak_position": 70}]