[{"work_id": "j_cole__stickz_n_stonez", "platform": "billboard", "chart_name": "hot_100", "region": "us", "date": "2024-04-20", "rank": 53, "streams": null, "weeks_on_chart": 1, "peak_position": 53}, {"work_id": "j_cole__stickz_n_stonez", "platform": "spotify", "chart_name": "top_200", "region": "global", "date": "2024-04-05", "rank": 66, "streams": 2021910, "weeks_on_chart": 1, "peak_position": 66}, {"work_id": "j_cole__stickz_n_stonez", "platform": "spotify", "chart_name": "top_200", "region": "us", "date": "2024-04-05", "rank": 18, "streams": 1227704, "weeks_on_chart": 1, "peak_position": 18}, {"work_id": "j_cole__stickz_n_stonez", "platform": "spotify", "chart_name": "top_200", "region": "us", "date": "2024-04-06", "rank": 48, "streams": 652166, "weeks_on_chart": 2, "peak_position": 18}, {"work_id": "j_cole__stickz_n_stonez", "platform": "spotify", "chart_name": "top_200", "region": "us", "date": "2024-04-07", "rank": 77, "streams": 455283, "weeks_on_chart": 3, "peak_position": 18}, {"work_id": "j_cole__stickz_n_stonez", "platform": "spotify", "chart_name": "top_200", "region": "us", "date": "2024-04-08", "rank": 114, "streams": 422689, "weeks_on_chart": 4, "peak_position": 18}]