[{"work_id": "lee_brice__one_of_them_girls", "platform": "billboard", "chart_name": "hot_100", "region": "us", "date": "2020-06-13", "rank": 90, "streams": null, "weeks_on_chart": 1, "peak_position": 90}, {"work_id": "lee_brice__one_of_them_girls", "platform": "billboard", "chart_name": "hot_100", "region": "us", "date": "2020-06-20", "rank": 94, "streams": null, "weeks_on_chart": 2, "peak_position": 90}, {"work_id": "lee_brice__one_of_them_girls", "platform": "billboard", "chart_name": "hot_100", "region": "us", "date": "2020-06-27", "rank": 98, "streams": null, "weeks_on_chart": 3, "peak_position": 90}, {"work_id": "lee_brice__one_of_them_girls", "platform": "billboard", "chart_name": "hot_100", "region": "us", "date": "2020-07-04", "rank": 81, "streams": null, "weeks_on_chart": 4, "peak_position": 81}, {"work_id": "lee_brice__one_of_them_girls", "platform": "billboard", "chart_name": "hot_100", "region": "us", "date": "2020-07-11", "rank": 73, "streams": null, "weeks_on_chart": 5, "peak_position": 73}, {"work_id": "lee_brice__one_of_them_girls", "platform": "billboard", "chart_name": "hot_100", "region": "us", "date": "2020-07-18", "rank": 87, "streams": null, "weeks_on_chart": 6, "peak_position": 73}, {"work_id": "lee_brice__one_of_them_girls", "platform": "billboard", "chart_name": "hot_100", "region": "us", "date": "2020-07-25", "rank": 78, "streams": null, "weeks_on_chart": 7, "peak_position": 73}, {"work_id": "lee_brice__one_of_them_girls", "platform": "billboard", "chart_name": "hot_100", "region": "us", "date": "2020-08-01", "rank": 69, "streams": null, "weeks_on_chart": 8, "peak_position": 69}, {"work_id": "lee_brice__one_of_them_girls", "platform": "billboard", "chart_name": "hot_100", "region": "us", "date": "2020-08-08", "rank": 83, "streams": null, "weeks_on_chart": 9, "peak_position": 69}, {"work_id": "lee_brice__one_of_them_girls", "platform": "billboard", "chart_name": "hot_100", "region": "us", "date": "2020-08-15", "rank": 61, "streams": null, "weeks_on_chart": 10, "peak_position": 61}, {"work_id": "lee_brice__one_of_them_girls", "platform": "billboard", "chart_name": "hot_100", "region": "us", "date": "2020-08-22", "rank": 59, "streams": null, "weeks_on_chart": 11, "peak_position": 59}, {"work_id": "lee_brice__one_of_them_girls", "platform": "billboard", "chart_name": "hot_100", "region": "us", "date": "2020-08-29", "rank": 52, "streams": null, "weeks_on_chart": 12, "peak_position": 52}, {"work_id": "lee_brice__one_of_them_girls", "platform": "billboard", "chart_name": "hot_100", "region": "us", "date": "2020-09-05", "rank": 46, "streams": null, "weeks_on_chart": 13, "peak_position": 46}, {"work_id": "lee_brice__one_of_them_girls", "platform": "billboard", "chart_name": "hot_100", "region": "us", "date": "2020-09-12", "rank": 33, "streams": null, "weeks_on_chart": 14, "peak_position": 33}, {"work_id": "lee_brice__one_of_them_girls", "platform": "billboard", "chart_name": "hot_100", "region": "us", "date": "2020-09-19", "rank": 22, "streams": null, "weeks_on_chart": 15, "peak_position": 22}, {"work_id": "lee_brice__one_of_them_girls", "platform": "billboard", "chart_name": "hot_100", "region": "us", "date": "2020-09-26", "rank": 19, "streams": null, "weeks_on_chart": 16, "peak_position": 19}, {"work_id": "lee_brice__one_of_them_girls", "platform": "billboard", "chart_name": "hot_100", "region": "us", "date": "2020-10-03", "rank": 22, "streams": null, "weeks_on_chart": 17, "peak_position": 19}, {"work_id": "lee_brice__one_of_them_girls", "platform": "billboard", "chart_name": "hot_100", "region": "us", "date": "2020-10-10", "rank": 18, "streams": null, "weeks_on_chart": 18, "peak_position": 18}, {"work_id": "lee_brice__one_of_them_girls", "platform": "billboard", "chart_name": "hot_100", "region": "us", "date": "2020-10-17", "rank": 20, "streams": null, "weeks_on_chart": 19, "peak_position": 18}, {"work_id": "lee_brice__one_of_them_girls", "platform": "billboard", "chart_name": "hot_100", "region": "us", "date": "2020-10-24", "rank": 17, "streams": null, "weeks_on_chart": 20, "peak_position": 17}, {"work_id": "lee_brice__one_of_them_girls", "platform": "billboard", "chart_name": "hot_100", "region": "us", "date": "2020-10-31", "rank": 17, "streams": null, "weeks_on_chart": 21, "peak_position": 17}, {"work_id": "lee_brice__one_of_them_girls", "platform": "billboard", "chart_name": "hot_100", "region": "us", "date": "2020-11-07", "rank": 26, "streams": null, "weeks_on_chart": 22, "peak_position": 17}, {"work_id": "lee_brice__one_of_them_girls", "platform": "billboard", "chart_name": "hot_100", "region": "us", "date": "2020-11-14", "rank": 27, "streams": null, "weeks_on_chart": 23, "peak_position": 17}, {"work_id": "lee_brice__one_of_them_girls", "platform": "billboard", "chart_name": "hot_100", "region": "us", "date": "2020-11-21", "rank": 29, "streams": null, "weeks_on_chart": 24, "peak_position": 17}, {"work_id": "lee_brice__one_of_them_girls", "platform": "billboard", "chart_name": "hot_100", "region": "us", "date": "2020-11-28", "rank": 33, "streams": null, "weeks_on_chart": 25, "peak_position": 17}, {"work_id": "lee_brice__one_of_them_girls", "platform": "billboard", "chart_name": "hot_100", "region": "us", "date": "2020-12-05", "rank": 40, "streams": null, "weeks_on_chart": 26, "peak_position": 17}, {"work_id": "lee_brice__one_of_them_girls", "platform": "spotify", "chart_name": "top_200", "region": "us", "date": "2020-05-30", "rank": 133, "streams": 256558, "weeks_on_chart": 1, "peak_position": 133}, {"work_id": "lee_brice__one_of_them_girls", "platform": "spotify", "chart_name": "top_200", "region": "us", "date": "2020-05-31", "rank": 132, "streams": 232456, "weeks_on_chart": 2, "peak_position": 132}, {"work_id": "lee_brice__one_of_them_girls", "platform": "spotify", "chart_name": "top_200", "region": "us", "date": "2020-06-01", "rank": 148, "streams": 224406, "weeks_on_chart": 3, "peak_position": 132}, {"work_id": "lee_brice__one_of_them_girls", "platform": "spotify", "chart_name": "top_200", "region": "us", "date": "2020-06-02", "rank": 172, "streams": 211869, "weeks_on_chart": 4, "peak_position": 132}, {"work_id": "lee_brice__one_of_them_girls", "platform": "spotify", "chart_name": "top_200", "region": "us", "date": "2020-06-03", "rank": 145, "streams": 228627, "weeks_on_chart": 5, "peak_position": 132}, {"work_id": "lee_brice__one_of_them_girls", "platform": "spotify", "chart_name": "top_200", "region": "us", "date": "2020-06-04", "rank": 149, "streams": 236162, "weeks_on_chart": 6, "peak_position": 132}, {"work_id": "lee_brice__one_of_them_girls", "platform": "spotify", "chart_name": "top_200", "region": "us", "date": "2020-06-05", "rank": 189, "streams": 217237, "weeks_on_chart": 7, "peak_position": 132}, {"work_id": "lee_brice__one_of_them_girls", "platform": "spotify", "chart_name": "top_200", "region": "us", "date": "2020-08-14", "rank": 172, "streams": 246937, "weeks_on_chart": 8, "peak_position": 132}, {"work_id": "lee_brice__one_of_them_girls", "platform": "spotify", "chart_name": "top_200", "region": "us", "date": "2020-08-15", "rank": 156, "streams": 242930, "weeks_on_chart": 9, "peak_position": 132}, {"work_id": "lee_brice__one_of_them_girls", "platform": "spotify", "chart_name": "top_200", "region": "us", "date": "2020-08-16", "rank": 165, "streams": 217080, "weeks_on_chart": 10, "peak_position": 132}, {"work_id": "lee_brice__one_of_them_girls", "platform": "spotify", "chart_name": "top_200", "region": "us", "date": "2020-08-17", "rank": 169, "streams": 224927, "weeks_on_chart": 11, "peak_position": 132}, {"work_id": "lee_brice__one_of_them_girls", "platform": "spotify", "chart_name": "top_200", "region": "us", "date": "2020-08-18", "rank": 170, "streams": 227937, "weeks_on_chart": 12, "peak_position": 132}, {"work_id": "lee_brice__one_of_them_girls", "platform": "spotify", "chart_name": "top_200", "region": "us", "date": "2020-08-19", "rank": 172, "streams": 222724, "weeks_on_chart": 13, "peak_position": 132}, {"work_id": "lee_brice__one_of_them_girls", "platform": "spotify", "chart_name": "top_200", "region": "us", "date": "2020-08-20", "rank": 166, "streams": 227219, "weeks_on_chart": 14, "peak_position": 132}, {"work_id": "lee_brice__one_of_them_girls", "platform": "spotify", "chart_name": "top_200", "region": "us", "date": "2020-08-21", "rank": 185, "streams": 228779, "weeks_on_chart": 15, "peak_position": 132}, {"work_id": "lee_brice__one_of_them_girls", "platform": "spotify", "chart_name": "top_200", "region": "us", "date": "2020-08-29", "rank": 180, "streams": 220152, "weeks_on_chart": 16, "peak_position": 132}, {"work_id": "lee_brice__one_of_them_girls", "platform": "spotify", "chart_name": "top_200", "region": "us", "date": "2020-08-30", "rank": 153, "streams": 224923, "weeks_on_chart": 17, "peak_position": 132}, {"work_id": "lee_brice__one_of_them_girls", "platform": "spotify", "chart_name": "top_200", "region": "us", "date": "2020-08-31", "rank": 147, "streams": 229799, "weeks_on_chart": 18, "peak_position": 132}, {"work_id": "lee_brice__one_of_them_girls", "platform": "spotify", "chart_name": "top_200", "region": "us", "date": "2020-09-01", "rank": 149, "streams": 231928, "weeks_on_chart": 19, "peak_position": 132}, {"work_id": "lee_brice__one_of_them_girls", "platform": "spotify", "chart_name": "top_200", "region": "us", "date": "2020-09-02", "rank": 150, "streams": 235498, "weeks_on_chart": 20, "peak_position": 132}, {"work_id": "lee_brice__one_of_them_girls", "platform": "spotify", "chart_name": "top_200", "region": "us", "date": "2020-09-03", "rank": 139, "streams": 248599, "weeks_on_chart": 21, "peak_position": 132}, {"work_id": "lee_brice__one_of_them_girls", "platform": "spotify", "chart_name": "top_200", "region": "us", "date": "2020-09-04", "rank": 145, "streams": 282805, "weeks_on_chart": 22, "peak_position": 132}, {"work_id": "lee_brice__one_of_them_girls", "platform": "spotify", "chart_name": "top_200", "region": "us", "date": "2020-09-05", "rank": 118, "streams": 289737, "weeks_on_chart": 23, "peak_position": 118}, {"work_id": "lee_brice__one_of_them_girls", "platform": "spotify", "chart_name": "top_200", "region": "us", "date": "2020-09-06", "rank": 115, "streams": 258206, "weeks_on_chart": 24, "peak_position": 115}, {"work_id": "lee_brice__one_of_them_girls", "platform": "spotify", "chart_name": "top_200", "region": "us", "date": "2020-09-07", "rank": 105, "streams": 268800, "weeks_on_chart": 25, "peak_position": 105}, {"work_id": "lee_brice__one_of_them_girls", "platform": "spotify", "chart_name": "top_200", "region": "us", "date": "2020-09-08", "rank": 107, "streams": 261931, "weeks_on_chart": 26, "peak_position": 105}, {"work_id": "lee_brice__one_of_them_girls", "platform": "spotify", "chart_name": "top_200", "region": "us", "date": "2020-09-09", "rank": 118, "streams": 256106, "weeks_on_chart": 27, "peak_position": 105}, {"work_id": "lee_brice__one_of_them_girls", "platform": "spotify", "chart_name": "top_200", "region": "us", "date": "2020-09-10", "rank": 117, "streams": 259575, "weeks_on_chart": 28, "peak_position": 105}, {"work_id": "lee_brice__one_of_them_girls", "platform": "spotify", "chart_name": "top_200", "region": "us", "date": "2020-09-11", "rank": 164, "streams": 243133, "weeks_on_chart": 29, "peak_position": 105}, {"work_id": "lee_brice__one_of_them_girls", "platform": "spotify", "chart_name": "top_200", "region": "us", "date": "2020-09-12", "rank": 168, "streams": 228012, "weeks_on_chart": 30, "peak_position": 105}, {"work_id": "lee_brice__one_of_them_girls", "platform": "spotify", "chart_name": "top_200", "region": "us", "date": "2020-09-13", "rank": 175, "streams": 200208, "weeks_on_chart": 31, "peak_position": 105}, {"work_id": "lee_brice__one_of_them_girls", "platform": "spotify", "chart_name": "top_200", "region": "us", "date": "2020-09-14", "rank": 151, "streams": 225092, "weeks_on_chart": 32, "peak_position": 105}, {"work_id": "lee_brice__one_of_them_girls", "platform": "spotify", "chart_name": "top_200", "region": "us", "date": "2020-09-15", "rank": 149, "streams": 228770, "weeks_on_chart": 33, "peak_position": 105}, {"work_id": "lee_brice__one_of_them_girls", "platform": "spotify", "chart_name": "top_200", "region": "us", "date": "2020-09-16", "rank": 144, "streams": 235802, "weeks_on_chart": 34, "peak_position": 105}, {"work_id": "lee_brice__one_of_them_girls", "platform": "spotify", "chart_name": "top_200", "region": "us", "date": "2020-09-17", "rank": 138, "streams": 241957, "weeks_on_chart": 35, "peak_position": 105}, {"work_id": "lee_brice__one_of_them_girls", "platform": "spotify", "chart_name": "top_200", "region": "us", "date": "2020-09-18", "rank": 146, "streams": 259708, "weeks_on_chart": 36, "peak_position": 105}, {"work_id": "lee_brice__one_of_them_girls", "platform": "spotify", "chart_name": "top_200", "region": "us", "date": "2020-09-19", "rank": 143, "streams": 250570, "weeks_on_chart": 37, "peak_position": 105}, {"work_id": "lee_brice__one_of_them_girls", "platform": "spotify", "chart_name": "top_200", "region": "us", "date": "2020-09-20", "rank": 159, "streams": 214522, "weeks_on_chart": 38, "peak_position": 105}, {"work_id": "lee_brice__one_of_them_girls", "platform": "spotify", "chart_name": "top_200", "region": "us", "date": "2020-09-21", "rank": 131, "streams": 237876, "weeks_on_chart": 39, "peak_position": 105}, {"work_id": "lee_brice__one_of_them_girls", "platform": "spotify", "chart_name": "top_200", "region": "us", "date": "2020-09-22", "rank": 133, "streams": 243420, "weeks_on_chart": 40, "peak_position": 105}, {"work_id": "lee_brice__one_of_them_girls", "platform": "spotify", "chart_name": "top_200", "region": "us", "date": "2020-09-23", "rank": 139, "streams": 242226, "weeks_on_chart": 41, "peak_position": 105}, {"work_id": "lee_brice__one_of_them_girls", "platform": "spotify", "chart_name": "top_200", "region": "us", "date": "2020-09-24", "rank": 128, "streams": 249145, "weeks_on_chart": 42, "peak_position": 105}, {"work_id": "lee_brice__one_of_them_girls", "platform": "spotify", "chart_name": "top_200", "region": "us", "date": "2020-09-25", "rank": 157, "streams": 267109, "weeks_on_chart": 43, "peak_position": 105}, {"work_id": "lee_brice__one_of_them_girls", "platform": "spotify", "chart_name": "top_200", "region": "us", "date": "2020-09-26", "rank": 162, "streams": 248904, "weeks_on_chart": 44, "peak_position": 105}, {"work_id": "lee_brice__one_of_them_girls", "platform": "spotify", "chart_name": "top_200", "region": "us", "date": "2020-09-27", "rank": 169, "streams": 217776, "weeks_on_chart": 45, "peak_position": 105}, {"work_id": "lee_brice__one_of_them_girls", "platform": "spotify", "chart_name": "top_200", "region": "us", "date": "2020-09-28", "rank": 157, "streams": 234797, "weeks_on_chart": 46, "peak_position": 105}, {"work_id": "lee_brice__one_of_them_girls", "platform": "spotify", "chart_name": "top_200", "region": "us", "date": "2020-09-29", "rank": 151, "streams": 238359, "weeks_on_chart": 47, "peak_position": 105}, {"work_id": "lee_brice__one_of_them_girls", "platform": "spotify", "chart_name": "top_200", "region": "us", "date": "2020-09-30", "rank": 131, "streams": 244998, "weeks_on_chart": 48, "peak_position": 105}, {"work_id": "lee_brice__one_of_them_girls", "platform": "spotify", "chart_name": "top_200", "region": "us", "date": "2020-10-01", "rank": 124, "streams": 258181, "weeks_on_chart": 49, "peak_position": 105}, {"work_id": "lee_brice__one_of_them_girls", "platform": "spotify", "chart_name": "top_200", "region": "us", "date": "2020-10-02", "rank": 148, "streams": 280373, "weeks_on_chart": 50, "peak_position": 105}, {"work_id": "lee_brice__one_of_them_girls", "platform": "spotify", "chart_name": "top_200", "region": "us", "date": "2020-10-03", "rank": 144, "streams": 266107, "weeks_on_chart": 51, "peak_position": 105}, {"work_id": "lee_brice__one_of_them_girls", "platform": "spotify", "chart_name": "top_200", "region": "us", "date": "2020-10-04", "rank": 147, "streams": 230250, "weeks_on_chart": 52, "peak_position": 105}, {"work_id": "lee_brice__one_of_them_girls", "platform": "spotify", "chart_name": "top_200", "region": "us", "date": "2020-10-05", "rank": 133, "streams": 250678, "weeks_on_chart": 53, "peak_position": 105}, {"work_id": "lee_brice__one_of_them_girls", "platform": "spotify", "chart_name": "top_200", "region": "us", "date": "2020-10-06", "rank": 128, "streams": 258061, "weeks_on_chart": 54, "peak_position": 105}, {"work_id": "lee_brice__one_of_them_girls", "platform": "spotify", "chart_name": "top_200", "region": "us", "date": "2020-10-07", "rank": 119, "streams": 267453, "weeks_on_chart": 55, "peak_position": 105}, {"work_id": "lee_brice__one_of_them_girls", "platform": "spotify", "chart_name": "top_200", "region": "us", "date": "2020-10-08", "rank": 113, "streams": 272443, "weeks_on_chart": 56, "peak_position": 105}, {"work_id": "lee_brice__one_of_them_girls", "platform": "spotify", "chart_name": "top_200", "region": "us", "date": "2020-10-09", "rank": 102, "streams": 300780, "weeks_on_chart": 57, "peak_position": 102}, {"work_id": "lee_brice__one_of_them_girls", "platform": "spotify", "chart_name": "top_200", "region": "us", "date": "2020-10-10", "rank": 88, "streams": 301983, "weeks_on_chart": 58, "peak_position": 88}, {"work_id": "lee_brice__one_of_them_girls", "platform": "spotify", "chart_name": "top_200", "region": "us", "date": "2020-10-11", "rank": 90, "streams": 267609, "weeks_on_chart": 59, "peak_position": 88}, {"work_id": "lee_brice__one_of_them_girls", "platform": "spotify", "chart_name": "top_200", "region": "us", "date": "2020-10-12", "rank": 77, "streams": 291389, "weeks_on_chart": 60, "peak_position": 77}, {"work_id": "lee_brice__one_of_them_girls", "platform": "spotify", "chart_name": "top_200", "region": "us", "date": "2020-10-13", "rank": 74, "streams": 301096, "weeks_on_chart": 61, "peak_position": 74}, {"work_id": "lee_brice__one_of_them_girls", "platform": "spotify", "chart_name": "top_200", "region": "us", "date": "2020-10-14", "rank": 68, "streams": 313755, "weeks_on_chart": 62, "peak_position": 68}, {"work_id": "lee_brice__one_of_them_girls", "platform": "spotify", "chart_name": "top_200", "region": "us", "date": "2020-10-15", "rank": 75, "streams": 314825, "weeks_on_chart": 63, "peak_position": 68}, {"work_id": "lee_brice__one_of_them_girls", "platform": "spotify", "chart_name": "top_200", "region": "us", "date": "2020-10-16", "rank": 80, "streams": 325125, "weeks_on_chart": 64, "peak_position": 68}, {"work_id": "lee_brice__one_of_them_girls", "platform": "spotify", "chart_name": "top_200", "region": "us", "date": "2020-10-17", "rank": 73, "streams": 319812, "weeks_on_chart": 65, "peak_position": 68}, {"work_id": "lee_brice__one_of_them_girls", "platform": "spotify", "chart_name": "top_200", "region": "us", "date": "2020-10-18", "rank": 77, "streams": 281611, "weeks_on_chart": 66, "peak_position": 68}, {"work_id": "lee_brice__one_of_them_girls", "platform": "spotify", "chart_name": "top_200", "region": "us", "date": "2020-10-19", "rank": 59, "streams": 316069, "weeks_on_chart": 67, "peak_position": 59}, {"work_id": "lee_brice__one_of_them_girls", "platform": "spotify", "chart_name": "top_200", "region": "us", "date": "2020-10-20", "rank": 53, "streams": 327260, "weeks_on_chart": 68, "peak_position": 53}, {"work_id": "lee_brice__one_of_them_girls", "platform": "spotify", "chart_name": "top_200", "region": "us", "date": "2020-10-21", "rank": 54, "streams": 327862, "weeks_on_chart": 69, "peak_position": 53}, {"work_id": "lee_brice__one_of_them_girls", "platform": "spotify", "chart_name": "top_200", "region": "us", "date": "2020-10-22", "rank": 55, "streams": 332267, "weeks_on_chart": 70, "peak_position": 53}, {"work_id": "lee_brice__one_of_them_girls", "platform": "spotify", "chart_name": "top_200", "region": "us", "date": "2020-10-23", "rank": 77, "streams": 332798, "weeks_on_chart": 71, "peak_position": 53}, {"work_id": "lee_brice__one_of_them_girls", "platform": "spotify", "chart_name": "top_200", "region": "us", "date": "2020-10-24", "rank": 92, "streams": 294884, "weeks_on_chart": 72, "peak_position": 53}, {"work_id": "lee_brice__one_of_them_girls", "platform": "spotify", "chart_name": "top_200", "region": "us", "date": "2020-10-25", "rank": 97, "streams": 254972, "weeks_on_chart": 73, "peak_position": 53}, {"work_id": "lee_brice__one_of_them_girls", "platform": "spotify", "chart_name": "top_200", "region": "us", "date": "2020-10-26", "rank": 85, "streams": 277520, "weeks_on_chart": 74, "peak_position": 53}, {"work_id": "lee_brice__one_of_them_girls", "platform": "spotify", "chart_name": "top_200", "region": "us", "date": "2020-10-27", "rank": 83, "streams": 284313, "weeks_on_chart": 75, "peak_position": 53}, {"work_id": "lee_brice__one_of_them_girls", "platform": "spotify", "chart_name": "top_200", "region": "us", "date": "2020-10-28", "rank": 84, "streams": 283058, "weeks_on_chart": 76, "peak_position": 53}, {"work_id": "lee_brice__one_of_them_girls", "platform": "spotify", "chart_name": "top_200", "region": "us", "date": "2020-10-29", "rank": 84, "streams": 288115, "weeks_on_chart": 77, "peak_position": 53}, {"work_id": "lee_brice__one_of_them_girls", "platform": "spotify", "chart_name": "top_200", "region": "us", "date": "2020-10-30", "rank": 124, "streams": 297824, "weeks_on_chart": 78, "peak_position": 53}, {"work_id": "lee_brice__one_of_them_girls", "platform": "spotify", "chart_name": "top_200", "region": "us", "date": "2020-10-31", "rank": 156, "streams": 267767, "weeks_on_chart": 79, "peak_position": 53}, {"work_id": "lee_brice__one_of_them_girls", "platform": "spotify", "chart_name": "top_200", "region": "us", "date": "2020-11-01", "rank": 157, "streams": 211414, "weeks_on_chart": 80, "peak_position": 53}, {"work_id": "lee_brice__one_of_them_girls", "platform": "spotify", "chart_name": "top_200", "region": "us", "date": "2020-11-02", "rank": 114, "streams": 253364, "weeks_on_chart": 81, "peak_position": 53}, {"work_id": "lee_brice__one_of_them_girls", "platform": "spotify", "chart_name": "top_200", "region": "us", "date": "2020-11-03", "rank": 112, "streams": 264457, "weeks_on_chart": 82, "peak_position": 53}, {"work_id": "lee_brice__one_of_them_girls", "platform": "spotify", "chart_name": "top_200", "region": "us", "date": "2020-11-04", "rank": 112, "streams": 246907, "weeks_on_chart": 83, "peak_position": 53}, {"work_id": "lee_brice__one_of_them_girls", "platform": "spotify", "chart_name": "top_200", "region": "us", "date": "2020-11-05", "rank": 109, "streams": 262369, "weeks_on_chart": 84, "peak_position": 53}, {"work_id": "lee_brice__one_of_them_girls", "platform": "spotify", "chart_name": "top_200", "region": "us", "date": "2020-11-06", "rank": 122, "streams": 281219, "weeks_on_chart": 85, "peak_position": 53}, {"work_id": "lee_brice__one_of_them_girls", "platform": "spotify", "chart_name": "top_200", "region": "us", "date": "2020-11-07", "rank": 126, "streams": 275080, "weeks_on_chart": 86, "peak_position": 53}, {"work_id": "lee_brice__one_of_them_girls", "platform": "spotify", "chart_name": "top_200", "region": "us", "date": "2020-11-08", "rank": 139, "streams": 238273, "weeks_on_chart": 87, "peak_position": 53}, {"work_id": "lee_brice__one_of_them_girls", "platform": "spotify", "chart_name": "top_200", "region": "us", "date": "2020-11-09", "rank": 123, "streams": 256175, "weeks_on_chart": 88, "peak_position": 53}, {"work_id": "lee_brice__one_of_them_girls", "platform": "spotify", "chart_name": "top_200", "region": "us", "date": "2020-11-10", "rank": 123, "streams": 259597, "weeks_on_chart": 89, "peak_position": 53}, {"work_id": "lee_brice__one_of_them_girls", "platform": "spotify", "chart_name": "top_200", "region": "us", "date": "2020-11-11", "rank": 133, "streams": 251549, "weeks_on_chart": 90, "peak_position": 53}, {"work_id": "lee_brice__one_of_them_girls", "platform": "spotify", "chart_name": "top_200", "region": "us", "date": "2020-11-12", "rank": 133, "streams": 256823, "weeks_on_chart": 91, "peak_position": 53}, {"work_id": "lee_brice__one_of_them_girls", "platform": "spotify", "chart_name": "top_200", "region": "us", "date": "2020-11-13", "rank": 131, "streams": 273055, "weeks_on_chart": 92, "peak_position": 53}, {"work_id": "lee_brice__one_of_them_girls", "platform": "spotify", "chart_name": "top_200", "region": "us", "date": "2020-11-14", "rank": 115, "streams": 279858, "weeks_on_chart": 93, "peak_position": 53}, {"work_id": "lee_brice__one_of_them_girls", "platform": "spotify", "chart_name": "top_200", "region": "us", "date": "2020-11-15", "rank": 123, "streams": 240509, "weeks_on_chart": 94, "peak_position": 53}, {"work_id": "lee_brice__one_of_them_girls", "platform": "spotify", "chart_name": "top_200", "region": "us", "date": "2020-11-16", "rank": 102, "streams": 267175, "weeks_on_chart": 95, "peak_position": 53}, {"work_id": "lee_brice__one_of_them_girls", "platform": "spotify", "chart_name": "top_200", "region": "us", "date": "2020-11-17", "rank": 102, "streams": 269331, "weeks_on_chart": 96, "peak_position": 53}, {"work_id": "lee_brice__one_of_them_girls", "platform": "spotify", "chart_name": "top_200", "region": "us", "date": "2020-11-18", "rank": 101, "streams": 270568, "weeks_on_chart": 97, "peak_position": 53}, {"work_id": "lee_brice__one_of_them_girls", "platform": "spotify", "chart_name": "top_200", "region": "us", "date": "2020-11-19", "rank": 104, "streams": 271085, "weeks_on_chart": 98, "peak_position": 53}, {"work_id": "lee_brice__one_of_them_girls", "platform": "spotify", "chart_name": "top_200", "region": "us", "date": "2020-11-20", "rank": 100, "streams": 317321, "weeks_on_chart": 99, "peak_position": 53}, {"work_id": "lee_brice__one_of_them_girls", "platform": "spotify", "chart_name": "top_200", "region": "us", "date": "2020-11-21", "rank": 121, "streams": 291333, "weeks_on_chart": 100, "peak_position": 53}, {"work_id": "lee_brice__one_of_them_girls", "platform": "spotify", "chart_name": "top_200", "region": "us", "date": "2020-11-22", "rank": 137, "streams": 244027, "weeks_on_chart": 101, "peak_position": 53}, {"work_id": "lee_brice__one_of_them_girls", "platform": "spotify", "chart_name": "top_200", "region": "us", "date": "2020-11-23", "rank": 139, "streams": 247074, "weeks_on_chart": 102, "peak_position": 53}, {"work_id": "lee_brice__one_of_them_girls", "platform": "spotify", "chart_name": "top_200", "region": "us", "date": "2020-11-24", "rank": 143, "streams": 252702, "weeks_on_chart": 103, "peak_position": 53}, {"work_id": "lee_brice__one_of_them_girls", "platform": "spotify", "chart_name": "top_200", "region": "us", "date": "2020-11-25", "rank": 144, "streams": 262070, "weeks_on_chart": 104, "peak_position": 53}, {"work_id": "lee_brice__one_of_them_girls", "platform": "spotify", "chart_name": "top_200", "region": "us", "date": "2020-11-26", "rank": 199, "streams": 218993, "weeks_on_chart": 105, "peak_position": 53}, {"work_id": "lee_brice__one_of_them_girls", "platform": "spotify", "chart_name": "top_200", "region": "us", "date": "2020-12-06", "rank": 188, "streams": 238289, "weeks_on_chart": 106, "peak_position": 53}, {"work_id": "lee_brice__one_of_them_girls", "platform": "spotify", "chart_name": "top_200", "region": "us", "date": "2020-12-07", "rank": 153, "streams": 257957, "weeks_on_chart": 107, "peak_position": 53}, {"work_id": "lee_brice__one_of_them_girls", "platform": "spotify", "chart_name": "top_200", "region": "us", "date": "2020-12-08", "rank": 149, "streams": 264828, "weeks_on_chart": 108, "peak_position": 53}, {"work_id": "lee_brice__one_of_them_girls", "platform": "spotify", "chart_name": "top_200", "region": "us", "date": "2020-12-09", "rank": 138, "streams": 279355, "weeks_on_chart": 109, "peak_position": 53}, {"work_id": "lee_brice__one_of_them_girls", "platform": "spotify", "chart_name": "top_200", "region": "us", "date": "2020-12-10", "rank": 149, "streams": 276185, "weeks_on_chart": 110, "peak_position": 53}, {"work_id": "lee_brice__one_of_them_girls", "platform": "spotify", "chart_name": "top_200", "region": "us", "date": "2021-05-31", "rank": 151, "streams": 221649, "weeks_on_chart": 111, "peak_position": 53}, {"work_id": "lee_brice__one_of_them_girls", "platform": "spotify", "chart_name": "top_200", "region": "us", "date": "2021-06-05", "rank": 195, "streams": 221018, "weeks_on_chart": 112, "peak_position": 53}, {"work_id": "lee_brice__one_of_them_girls", "platform": "spotify", "chart_name": "top_200", "region": "us", "date": "2021-06-06", "rank": 196, "streams": 196561, "weeks_on_chart": 113, "peak_position": 53}, {"work_id": "lee_brice__one_of_them_girls", "platform": "spotify", "chart_name": "top_200", "region": "us", "date": "2021-06-13", "rank": 187, "streams": 210346, "weeks_on_chart": 114, "peak_position": 53}, {"work_id": "lee_brice__one_of_them_girls", "platform": "spotify", "chart_name": "top_200", "region": "us", "date": "2021-06-16", "rank": 190, "streams": 213967, "weeks_on_chart": 115, "peak_position": 53}, {"work_id": "lee_brice__one_of_them_girls", "platform": "spotify", "chart_name": "top_200", "region": "us", "date": "2021-06-17", "rank": 189, "streams": 219861, "weeks_on_chart": 116, "peak_position": 53}, {"work_id": "lee_brice__one_of_them_girls", "platform": "spotify", "chart_name": "top_200", "region": "us", "date": "2021-06-18", "rank": 184, "streams": 229631, "weeks_on_chart": 117, "peak_position": 53}, {"work_id": "lee_brice__one_of_them_girls", "platform": "spotify", "chart_name": "top_200", "region": "us", "date": "2021-06-19", "rank": 168, "streams": 223019, "weeks_on_chart": 118, "peak_position": 53}, {"work_id": "lee_brice__one_of_them_girls", "platform": "spotify", "chart_name": "top_200", "region": "us", "date": "2021-06-20", "rank": 159, "streams": 204420, "weeks_on_chart": 119, "peak_position": 53}, {"work_id": "lee_brice__one_of_them_girls", "platform": "spotify", "chart_name": "top_200", "region": "us", "date": "2021-06-21", "rank": 185, "streams": 201602, "weeks_on_chart": 120, "peak_position": 53}, {"work_id": "lee_brice__one_of_them_girls", "platform": "spotify", "chart_name": "top_200", "region": "us", "date": "2021-06-22", "rank": 195, "streams": 200307, "weeks_on_chart": 121, "peak_position": 53}, {"work_id": "lee_brice__one_of_them_girls", "platform": "spotify", "chart_name": "top_200", "region": "us", "date": "2021-06-23", "rank": 180, "streams": 210615, "weeks_on_chart": 122, "peak_position": 53}, {"work_id": "lee_brice__one_of_them_girls", "platform": "spotify", "chart_name": "top_200", "region": "us", "date": "2021-06-24", "rank": 173, "streams": 216620, "weeks_on_chart": 123, "peak_position": 53}, {"work_id": "lee_brice__one_of_them_girls", "platform": "spotify", "chart_name": "top_200", "region": "us", "date": "2021-06-26", "rank": 191, "streams": 218812, "weeks_on_chart": 124, "peak_position": 53}, {"work_id": "lee_brice__one_of_them_girls", "platform": "spotify", "chart_name": "top_200", "region": "us", "date": "2021-06-27", "rank": 185, "streams": 206405, "weeks_on_chart": 125, "peak_position": 53}, {"work_id": "lee_brice__one_of_them_girls", "platform": "spotify", "chart_name": "top_200", "region": "us", "date": "2021-07-03", "rank": 184, "streams": 218582, "weeks_on_chart": 126, "peak_position": 53}, {"work_id": "lee_brice__one_of_them_girls", "platform": "spotify", "chart_name": "top_200", "region": "us", "date": "2021-07-04", "rank": 186, "streams": 213068, "weeks_on_chart": 127, "peak_position": 53}, {"work_id": "lee_brice__one_of_them_girls", "platform": "spotify", "chart_name": "top_200", "region": "us", "date": "2021-07-05", "rank": 176, "streams": 209261, "weeks_on_chart": 128, "peak_position": 53}, {"work_id": "lee_brice__one_of_them_girls", "platform": "spotify", "chart_name": "top_200", "region": "us", "date": "2021-07-22", "rank": 197, "streams": 203053, "weeks_on_chart": 129, "peak_position": 53}, {"work_id": "lee_brice__one_of_them_girls", "platform": "spotify", "chart_name": "top_200", "region": "us", "date": "2021-07-24", "rank": 193, "streams": 211005, "weeks_on_chart": 130, "peak_position": 53}, {"work_id": "lee_brice__one_of_them_girls", "platform": "spotify", "chart_name": "top_200", "region": "us", "date": "2021-07-25", "rank": 196, "streams": 188550, "weeks_on_chart": 131, "peak_position": 53}]