[{"work_id": "uzi__arasan_da", "platform": "spotify", "chart_name": "top_200", "region": "global", "date": "2022-03-18", "rank": 55, "streams": 1417131, "weeks_on_chart": 1, "peak_position": 55}, {"work_id": "uzi__arasan_da", "platform": "spotify", "chart_name": "top_200", "region": "global", "date": "2022-03-19", "rank": 58, "streams": 1299313, "weeks_on_chart": 2, "peak_position": 55}, {"work_id": "uzi__arasan_da", "platform": "spotify", "chart_name": "top_200", "region": "global", "date": "2022-03-20", "rank": 54, "streams": 1181811, "weeks_on_chart": 3, "peak_position": 54}, {"work_id": "uzi__arasan_da", "platform": "spotify", "chart_name": "top_200", "region": "global", "date": "2022-03-21", "rank": 56, "streams": 1229069, "weeks_on_chart": 4, "peak_position": 54}, {"work_id": "uzi__arasan_da", "platform": "spotify", "chart_name": "top_200", "region": "global", "date": "2022-03-22", "rank": 74, "streams": 1136448, "weeks_on_chart": 5, "peak_position": 54}, {"work_id": "uzi__arasan_da", "platform": "spotify", "chart_name": "top_200", "region": "global", "date": "2022-03-23", "rank": 96, "streams": 1067957, "weeks_on_chart": 6, "peak_position": 54}, {"work_id": "uzi__arasan_da", "platform": "spotify", "chart_name": "top_200", "region": "global", "date": "2022-03-24", "rank": 110, "streams": 1012673, "weeks_on_chart": 7, "peak_position": 54}, {"work_id": "uzi__arasan_da", "platform": "spotify", "chart_name": "top_200", "region": "global", "date": "2022-03-25", "rank": 135, "streams": 1011871, "weeks_on_chart": 8, "peak_position": 54}, {"work_id": "uzi__arasan_da", "platform": "spotify", "chart_name": "top_200", "region": "global", "date": "2022-03-26", "rank": 135, "streams": 961075, "weeks_on_chart": 9, "peak_position": 54}, {"work_id": "uzi__arasan_da", "platform": "spotify", "chart_name": "top_200", "region": "global", "date": "2022-03-27", "rank": 121, "streams": 891180, "weeks_on_chart": 10, "peak_position": 54}, {"work_id": "uzi__arasan_da", "platform": "spotify", "chart_name": "top_200", "region": "global", "date": "2022-03-28", "rank": 127, "streams": 898279, "weeks_on_chart": 11, "peak_position": 54}, {"work_id": "uzi__arasan_da", "platform": "spotify", "chart_name": "top_200", "region": "global", "date": "2022-03-29", "rank": 143, "streams": 849614, "weeks_on_chart": 12, "peak_position": 54}, {"work_id": "uzi__arasan_da", "platform": "spotify", "chart_name": "top_200", "region": "global", "date": "2022-03-30", "rank": 146, "streams": 855151, "weeks_on_chart": 13, "peak_position": 54}, {"work_id": "uzi__arasan_da", "platform": "spotify", "chart_name": "top_200", "region": "global", "date": "2022-03-31", "rank": 173, "streams": 817258, "weeks_on_chart": 14, "peak_position": 54}, {"work_id": "uzi__arasan_da", "platform": "spotify", "chart_name": "top_200", "region": "global", "date": "2022-04-01", "rank": 192, "streams": 822956, "weeks_on_chart": 15, "peak_position": 54}]