[{"work_id": "drake__firm_friends", "platform": "spotify", "chart_name": "top_200", "region": "global", "date": "2026-05-15", "rank": 23, "streams": 4359688, "weeks_on_chart": 1, "peak_position": 23}, {"work_id": "drake__firm_friends", "platform": "spotify", "chart_name": "top_200", "region": "global", "date": "2026-05-16", "rank": 54, "streams": 2275480, "weeks_on_chart": 2, "peak_position": 23}, {"work_id": "drake__firm_friends", "platform": "spotify", "chart_name": "top_200", "region": "global", "date": "2026-05-17", "rank": 107, "streams": 1513381, "weeks_on_chart": 3, "peak_position": 23}, {"work_id": "drake__firm_friends", "platform": "spotify", "chart_name": "top_200", "region": "global", "date": "2026-05-18", "rank": 130, "streams": 1498750, "weeks_on_chart": 4, "peak_position": 23}, {"work_id": "drake__firm_friends", "platform": "spotify", "chart_name": "top_200", "region": "global", "date": "2026-05-19", "rank": 191, "streams": 1298055, "weeks_on_chart": 5, "peak_position": 23}, {"work_id": "drake__firm_friends", "platform": "spotify", "chart_name": "top_200", "region": "us", "date": "2026-05-15", "rank": 18, "streams": 2082278, "weeks_on_chart": 1, "peak_position": 18}, {"work_id": "drake__firm_friends", "platform": "spotify", "chart_name": "top_200", "region": "us", "date": "2026-05-16", "rank": 23, "streams": 1037362, "weeks_on_chart": 2, "peak_position": 18}, {"work_id": "drake__firm_friends", "platform": "spotify", "chart_name": "top_200", "region": "us", "date": "2026-05-17", "rank": 36, "streams": 655969, "weeks_on_chart": 3, "peak_position": 18}, {"work_id": "drake__firm_friends", "platform": "spotify", "chart_name": "top_200", "region": "us", "date": "2026-05-18", "rank": 49, "streams": 667483, "weeks_on_chart": 4, "peak_position": 18}, {"work_id": "drake__firm_friends", "platform": "spotify", "chart_name": "top_200", "region": "us", "date": "2026-05-19", "rank": 52, "streams": 581274, "weeks_on_chart": 5, "peak_position": 18}, {"work_id": "drake__firm_friends", "platform": "spotify", "chart_name": "top_200", "region": "us", "date": "2026-05-20", "rank": 77, "streams": 499594, "weeks_on_chart": 6, "peak_position": 18}, {"work_id": "drake__firm_friends", "platform": "spotify", "chart_name": "top_200", "region": "us", "date": "2026-05-21", "rank": 96, "streams": 450778, "weeks_on_chart": 7, "peak_position": 18}, {"work_id": "drake__firm_friends", "platform": "spotify", "chart_name": "top_200", "region": "us", "date": "2026-05-22", "rank": 117, "streams": 434411, "weeks_on_chart": 8, "peak_position": 18}, {"work_id": "drake__firm_friends", "platform": "spotify", "chart_name": "top_200", "region": "us", "date": "2026-05-23", "rank": 184, "streams": 350610, "weeks_on_chart": 9, "peak_position": 18}]